{
  "id": "reflection_meeting_20260204_040633_ceo",
  "timestamp": "2026-02-04T04:07:29.410356+00:00",
  "type": "reflection",
  "content": {
    "agent_id": "ceo",
    "session_id": "meeting_20260204_040633",
    "reflection_text": "# ุชูุฑูุฑ ุงููุฑุงุฌุนุฉ ุงูุฐุงุชูุฉ - ุงูุฑุฆูุณ ุงูุชูููุฐู\n\n## ูุนูููุงุช ุงูุงุฌุชูุงุน\n- **ูุนุฑู ุงูุฌูุณุฉ**: meeting_20260204_040633\n- **ุงูุชุงุฑูุฎ**: 2026-02-04T04:06:33.458731+00:00\n- **ุฏูุฑู**: CEO\n\n## ุงูุชูููู ุงูุฐุงุชู\n\n### ูุง ูุฌุญ โ\nุดุงุฑูุช ูู ุงูุงุฌุชูุงุน ููุฏูุช ูุณุงููุงุช ูู ูุฌุงู ุชุฎุตุตู (ุงูุงุณุชุฑุงุชูุฌูุฉ, ุงูููุงุฏุฉ, ุงูุฑุคูุฉ).\n\n### ูุง ูุดู โ\nูููููู ุชุญุณูู ุฌูุฏุฉ ูุณุงููุงุชู ูุชูุฏูู ุงููุฒูุฏ ูู ุงูุชูุงุตูู ุงูุชูููุฉ.\n\n### ุฎุทุฉ ุงูุชุญุณูู ๐\nุณุฃุฑูุฒ ุนูู ุชุทููุฑ ุฎุจุฑุชู ูู ุงูุงุณุชุฑุงุชูุฌูุฉ, ุงูููุงุฏุฉ, ุงูุฑุคูุฉ ูุชุญุณูู ุงูุชูุงุตู ูุน ุงููุฑูู.\n\n## ุฅุญุตุงุฆูุงุช ุงูุฃุฏุงุก\n- **ุนุฏุฏ ุงููุณุงููุงุช**: 3\n- **ุฏุฑุฌุฉ ุงูุณูุนุฉ ุงูุญุงููุฉ**: 1.00\n- **ูุฒู ุงูุชุตููุช**: 1.50\n\n---\n*ุชู ุฅูุชุงุฌ ูุฐุง ุงูุชูุฑูุฑ ูู 2026-02-04T04:07:23.567791+00:00*\n",
    "extracted_insights": {
      "successes": [
        "ุดุงุฑูุช ูู ุงูุงุฌุชูุงุน ููุฏูุช ูุณุงููุงุช ูู ูุฌุงู ุชุฎุตุตู (ุงูุงุณุชุฑุงุชูุฌูุฉ, ุงูููุงุฏุฉ, ุงูุฑุคูุฉ)."
      ],
      "failures": [],
      "improvements": [
        "- **ุนุฏุฏ ุงููุณุงููุงุช**: 3",
        "- **ุฏุฑุฌุฉ ุงูุณูุนุฉ ุงูุญุงููุฉ**: 1.00",
        "- **ูุฒู ุงูุชุตููุช**: 1.50",
        "---",
        "*ุชู ุฅูุชุงุฌ ูุฐุง ุงูุชูุฑูุฑ ูู 2026-02-04T04:07:23.567791+00:00*"
      ]
    }
  },
  "metadata": {
    "session_id": "meeting_20260204_040633",
    "agent_id": "ceo"
  },
  "tags": [
    "reflection",
    "ceo",
    "meeting_20260204_040633"
  ]
}