{
  "id": "reflection_meeting_20260204_032606_memory",
  "timestamp": "2026-02-04T03:26:06.331767+00:00",
  "type": "reflection",
  "content": {
    "agent_id": "memory",
    "session_id": "meeting_20260204_032606",
    "reflection_text": "# ุชูุฑูุฑ ุงููุฑุงุฌุนุฉ ุงูุฐุงุชูุฉ - ูุฏูุฑ ุงูุฐุงูุฑุฉ\n\n## ูุนูููุงุช ุงูุงุฌุชูุงุน\n- **ูุนุฑู ุงูุฌูุณุฉ**: meeting_20260204_032606\n- **ุงูุชุงุฑูุฎ**: 2026-02-04T03:26:06.284835+00:00\n- **ุฏูุฑู**: Memory Manager\n\n## ุงูุชูููู ุงูุฐุงุชู\n\n### ูุง ูุฌุญ โ\nุดุงุฑูุช ูู ุงูุงุฌุชูุงุน ููุฏูุช ูุณุงููุงุช ูู ูุฌุงู ุชุฎุตุตู.\n\n### ูุง ูุดู โ\nูููููู ุชุญุณูู ุฌูุฏุฉ ูุณุงููุงุชู ูุชูุฏูู ุงููุฒูุฏ ูู ุงูุชูุงุตูู.\n\n### ุฎุทุฉ ุงูุชุญุณูู ๐\nุณุฃุฑูุฒ ุนูู ุชุทููุฑ ุฎุจุฑุชู ูู ุฅุฏุงุฑุฉ ุงููุนุฑูุฉ, ุงูุฃุฑุดูุฉ, ุงูุงุณุชุฑุฌุงุน.\n\n## ุฅุญุตุงุฆูุงุช ุงูุฃุฏุงุก\n- **ุนุฏุฏ ุงููุณุงููุงุช**: 1\n- **ุฏุฑุฌุฉ ุงูุณูุนุฉ ุงูุญุงููุฉ**: 1.00\n- **ูุฒู ุงูุชุตููุช**: 0.00\n\n---\n*ุชู ุฅูุชุงุฌ ูุฐุง ุงูุชูุฑูุฑ ูู 2026-02-04T03:26:06.313633+00:00*\n",
    "extracted_insights": {
      "successes": [
        "ุดุงุฑูุช ูู ุงูุงุฌุชูุงุน ููุฏูุช ูุณุงููุงุช ูู ูุฌุงู ุชุฎุตุตู."
      ],
      "failures": [],
      "improvements": [
        "ุณุฃุฑูุฒ ุนูู ุชุทููุฑ ุฎุจุฑุชู ูู ุฅุฏุงุฑุฉ ุงููุนุฑูุฉ, ุงูุฃุฑุดูุฉ, ุงูุงุณุชุฑุฌุงุน.",
        "- **ุนุฏุฏ ุงููุณุงููุงุช**: 1",
        "- **ุฏุฑุฌุฉ ุงูุณูุนุฉ ุงูุญุงููุฉ**: 1.00",
        "- **ูุฒู ุงูุชุตููุช**: 0.00",
        "---",
        "*ุชู ุฅูุชุงุฌ ูุฐุง ุงูุชูุฑูุฑ ูู 2026-02-04T03:26:06.313633+00:00*"
      ]
    }
  },
  "metadata": {
    "session_id": "meeting_20260204_032606",
    "agent_id": "memory"
  },
  "tags": [
    "reflection",
    "memory",
    "meeting_20260204_032606"
  ]
}