{
  "id": "reflection_meeting_20260204_035753_ceo",
  "timestamp": "2026-02-04T03:58:30.090294+00:00",
  "type": "reflection",
  "content": {
    "agent_id": "ceo",
    "session_id": "meeting_20260204_035753",
    "reflection_text": "# ุชูุฑูุฑ ุงููุฑุงุฌุนุฉ ุงูุฐุงุชูุฉ - ุงูุฑุฆูุณ ุงูุชูููุฐู\n\n## ูุนูููุงุช ุงูุงุฌุชูุงุน\n- **ูุนุฑู ุงูุฌูุณุฉ**: meeting_20260204_035753\n- **ุงูุชุงุฑูุฎ**: 2026-02-04T03:57:53.802986+00:00\n- **ุฏูุฑู**: CEO\n\n## ุงูุชูููู ุงูุฐุงุชู\n\n### ูุง ูุฌุญ โ\nุดุงุฑูุช ูู ุงูุงุฌุชูุงุน ููุฏูุช ูุณุงููุงุช ูู ูุฌุงู ุชุฎุตุตู.\n\n### ูุง ูุดู โ\nูููููู ุชุญุณูู ุฌูุฏุฉ ูุณุงููุงุชู ูุชูุฏูู ุงููุฒูุฏ ูู ุงูุชูุงุตูู.\n\n### ุฎุทุฉ ุงูุชุญุณูู ๐\nุณุฃุฑูุฒ ุนูู ุชุทููุฑ ุฎุจุฑุชู ูู ุงูุงุณุชุฑุงุชูุฌูุฉ, ุงูููุงุฏุฉ, ุงูุฑุคูุฉ.\n\n## ุฅุญุตุงุฆูุงุช ุงูุฃุฏุงุก\n- **ุนุฏุฏ ุงููุณุงููุงุช**: 0\n- **ุฏุฑุฌุฉ ุงูุณูุนุฉ ุงูุญุงููุฉ**: 1.00\n- **ูุฒู ุงูุชุตููุช**: 1.50\n\n---\n*ุชู ุฅูุชุงุฌ ูุฐุง ุงูุชูุฑูุฑ ูู 2026-02-04T03:58:30.085286+00:00*\n",
    "extracted_insights": {
      "successes": [
        "ุดุงุฑูุช ูู ุงูุงุฌุชูุงุน ููุฏูุช ูุณุงููุงุช ูู ูุฌุงู ุชุฎุตุตู."
      ],
      "failures": [],
      "improvements": [
        "ุณุฃุฑูุฒ ุนูู ุชุทููุฑ ุฎุจุฑุชู ูู ุงูุงุณุชุฑุงุชูุฌูุฉ, ุงูููุงุฏุฉ, ุงูุฑุคูุฉ.",
        "- **ุนุฏุฏ ุงููุณุงููุงุช**: 0",
        "- **ุฏุฑุฌุฉ ุงูุณูุนุฉ ุงูุญุงููุฉ**: 1.00",
        "- **ูุฒู ุงูุชุตููุช**: 1.50",
        "---",
        "*ุชู ุฅูุชุงุฌ ูุฐุง ุงูุชูุฑูุฑ ูู 2026-02-04T03:58:30.085286+00:00*"
      ]
    }
  },
  "metadata": {
    "session_id": "meeting_20260204_035753",
    "agent_id": "ceo"
  },
  "tags": [
    "reflection",
    "ceo",
    "meeting_20260204_035753"
  ]
}