{
  "id": "reflection_meeting_20260204_040129_marketing",
  "timestamp": "2026-02-04T04:02:16.150241+00:00",
  "type": "reflection",
  "content": {
    "agent_id": "marketing",
    "session_id": "meeting_20260204_040129",
    "reflection_text": "# ุชูุฑูุฑ ุงููุฑุงุฌุนุฉ ุงูุฐุงุชูุฉ - ูุฎุชุต ุงูุชุณููู\n\n## ูุนูููุงุช ุงูุงุฌุชูุงุน\n- **ูุนุฑู ุงูุฌูุณุฉ**: meeting_20260204_040129\n- **ุงูุชุงุฑูุฎ**: 2026-02-04T04:01:29.926302+00:00\n- **ุฏูุฑู**: Marketing Specialist\n\n## ุงูุชูููู ุงูุฐุงุชู\n\n### ูุง ูุฌุญ โ\nุดุงุฑูุช ูู ุงูุงุฌุชูุงุน ููุฏูุช ูุณุงููุงุช ูู ูุฌุงู ุชุฎุตุตู (ุงูุชุณููู, ุงูุณูู, ุงูุนููุงุก).\n\n### ูุง ูุดู โ\nูููููู ุชุญุณูู ุฌูุฏุฉ ูุณุงููุงุชู ูุชูุฏูู ุงููุฒูุฏ ูู ุงูุชูุงุตูู ุงูุชูููุฉ.\n\n### ุฎุทุฉ ุงูุชุญุณูู ๐\nุณุฃุฑูุฒ ุนูู ุชุทููุฑ ุฎุจุฑุชู ูู ุงูุชุณููู, ุงูุณูู, ุงูุนููุงุก ูุชุญุณูู ุงูุชูุงุตู ูุน ุงููุฑูู.\n\n## ุฅุญุตุงุฆูุงุช ุงูุฃุฏุงุก\n- **ุนุฏุฏ ุงููุณุงููุงุช**: 0\n- **ุฏุฑุฌุฉ ุงูุณูุนุฉ ุงูุญุงููุฉ**: 1.00\n- **ูุฒู ุงูุชุตููุช**: 1.00\n\n---\n*ุชู ุฅูุชุงุฌ ูุฐุง ุงูุชูุฑูุฑ ูู 2026-02-04T04:02:14.457425+00:00*\n",
    "extracted_insights": {
      "successes": [
        "ุดุงุฑูุช ูู ุงูุงุฌุชูุงุน ููุฏูุช ูุณุงููุงุช ูู ูุฌุงู ุชุฎุตุตู (ุงูุชุณููู, ุงูุณูู, ุงูุนููุงุก)."
      ],
      "failures": [],
      "improvements": [
        "- **ุนุฏุฏ ุงููุณุงููุงุช**: 0",
        "- **ุฏุฑุฌุฉ ุงูุณูุนุฉ ุงูุญุงููุฉ**: 1.00",
        "- **ูุฒู ุงูุชุตููุช**: 1.00",
        "---",
        "*ุชู ุฅูุชุงุฌ ูุฐุง ุงูุชูุฑูุฑ ูู 2026-02-04T04:02:14.457425+00:00*"
      ]
    }
  },
  "metadata": {
    "session_id": "meeting_20260204_040129",
    "agent_id": "marketing"
  },
  "tags": [
    "reflection",
    "marketing",
    "meeting_20260204_040129"
  ]
}