{
  "id": "reflection_meeting_20260204_035945_critic",
  "timestamp": "2026-02-04T04:00:26.253429+00:00",
  "type": "reflection",
  "content": {
    "agent_id": "critic",
    "session_id": "meeting_20260204_035945",
    "reflection_text": "# ุชูุฑูุฑ ุงููุฑุงุฌุนุฉ ุงูุฐุงุชูุฉ - ุงููุงูุฏ\n\n## ูุนูููุงุช ุงูุงุฌุชูุงุน\n- **ูุนุฑู ุงูุฌูุณุฉ**: meeting_20260204_035945\n- **ุงูุชุงุฑูุฎ**: 2026-02-04T03:59:45.861939+00:00\n- **ุฏูุฑู**: Critic\n\n## ุงูุชูููู ุงูุฐุงุชู\n\n### ูุง ูุฌุญ โ\nุดุงุฑูุช ูู ุงูุงุฌุชูุงุน ููุฏูุช ูุณุงููุงุช ูู ูุฌุงู ุชุฎุตุตู.\n\n### ูุง ูุดู โ\nูููููู ุชุญุณูู ุฌูุฏุฉ ูุณุงููุงุชู ูุชูุฏูู ุงููุฒูุฏ ูู ุงูุชูุงุตูู.\n\n### ุฎุทุฉ ุงูุชุญุณูู ๐\nุณุฃุฑูุฒ ุนูู ุชุทููุฑ ุฎุจุฑุชู ูู ุงูุชุญููู ุงูููุฏู, ุชูููู ุงููุฎุงุทุฑ, ุงููุฑุงุฌุนุฉ.\n\n## ุฅุญุตุงุฆูุงุช ุงูุฃุฏุงุก\n- **ุนุฏุฏ ุงููุณุงููุงุช**: 0\n- **ุฏุฑุฌุฉ ุงูุณูุนุฉ ุงูุญุงููุฉ**: 1.00\n- **ูุฒู ุงูุชุตููุช**: 1.10\n\n---\n*ุชู ุฅูุชุงุฌ ูุฐุง ุงูุชูุฑูุฑ ูู 2026-02-04T04:00:26.237085+00:00*\n",
    "extracted_insights": {
      "successes": [
        "ุดุงุฑูุช ูู ุงูุงุฌุชูุงุน ููุฏูุช ูุณุงููุงุช ูู ูุฌุงู ุชุฎุตุตู."
      ],
      "failures": [],
      "improvements": [
        "ุณุฃุฑูุฒ ุนูู ุชุทููุฑ ุฎุจุฑุชู ูู ุงูุชุญููู ุงูููุฏู, ุชูููู ุงููุฎุงุทุฑ, ุงููุฑุงุฌุนุฉ.",
        "- **ุนุฏุฏ ุงููุณุงููุงุช**: 0",
        "- **ุฏุฑุฌุฉ ุงูุณูุนุฉ ุงูุญุงููุฉ**: 1.00",
        "- **ูุฒู ุงูุชุตููุช**: 1.10",
        "---",
        "*ุชู ุฅูุชุงุฌ ูุฐุง ุงูุชูุฑูุฑ ูู 2026-02-04T04:00:26.237085+00:00*"
      ]
    }
  },
  "metadata": {
    "session_id": "meeting_20260204_035945",
    "agent_id": "critic"
  },
  "tags": [
    "reflection",
    "critic",
    "meeting_20260204_035945"
  ]
}