{
  "id": "reflection_meeting_20260204_035945_chair",
  "timestamp": "2026-02-04T04:00:26.254908+00:00",
  "type": "reflection",
  "content": {
    "agent_id": "chair",
    "session_id": "meeting_20260204_035945",
    "reflection_text": "# ุชูุฑูุฑ ุงููุฑุงุฌุนุฉ ุงูุฐุงุชูุฉ - ุฑุฆูุณ ุงูุงุฌุชูุงุน\n\n## ูุนูููุงุช ุงูุงุฌุชูุงุน\n- **ูุนุฑู ุงูุฌูุณุฉ**: meeting_20260204_035945\n- **ุงูุชุงุฑูุฎ**: 2026-02-04T03:59:45.861939+00:00\n- **ุฏูุฑู**: Meeting Chair\n\n## ุงูุชูููู ุงูุฐุงุชู\n\n### ูุง ูุฌุญ โ\nุดุงุฑูุช ูู ุงูุงุฌุชูุงุน ููุฏูุช ูุณุงููุงุช ูู ูุฌุงู ุชุฎุตุตู.\n\n### ูุง ูุดู โ\nูููููู ุชุญุณูู ุฌูุฏุฉ ูุณุงููุงุชู ูุชูุฏูู ุงููุฒูุฏ ูู ุงูุชูุงุตูู.\n\n### ุฎุทุฉ ุงูุชุญุณูู ๐\nุณุฃุฑูุฒ ุนูู ุชุทููุฑ ุฎุจุฑุชู ูู ุฅุฏุงุฑุฉ ุงูุงุฌุชูุงุนุงุช, ุงูุชูุณูู, ุงุชุฎุงุฐ ุงููุฑุงุฑุงุช.\n\n## ุฅุญุตุงุฆูุงุช ุงูุฃุฏุงุก\n- **ุนุฏุฏ ุงููุณุงููุงุช**: 0\n- **ุฏุฑุฌุฉ ุงูุณูุนุฉ ุงูุญุงููุฉ**: 1.00\n- **ูุฒู ุงูุชุตููุช**: 1.00\n\n---\n*ุชู ุฅูุชุงุฌ ูุฐุง ุงูุชูุฑูุฑ ูู 2026-02-04T04:00:26.237088+00:00*\n",
    "extracted_insights": {
      "successes": [
        "ุดุงุฑูุช ูู ุงูุงุฌุชูุงุน ููุฏูุช ูุณุงููุงุช ูู ูุฌุงู ุชุฎุตุตู."
      ],
      "failures": [],
      "improvements": [
        "ุณุฃุฑูุฒ ุนูู ุชุทููุฑ ุฎุจุฑุชู ูู ุฅุฏุงุฑุฉ ุงูุงุฌุชูุงุนุงุช, ุงูุชูุณูู, ุงุชุฎุงุฐ ุงููุฑุงุฑุงุช.",
        "- **ุนุฏุฏ ุงููุณุงููุงุช**: 0",
        "- **ุฏุฑุฌุฉ ุงูุณูุนุฉ ุงูุญุงููุฉ**: 1.00",
        "- **ูุฒู ุงูุชุตููุช**: 1.00",
        "---",
        "*ุชู ุฅูุชุงุฌ ูุฐุง ุงูุชูุฑูุฑ ูู 2026-02-04T04:00:26.237088+00:00*"
      ]
    }
  },
  "metadata": {
    "session_id": "meeting_20260204_035945",
    "agent_id": "chair"
  },
  "tags": [
    "reflection",
    "chair",
    "meeting_20260204_035945"
  ]
}