{
  "id": "reflection_meeting_20260204_035056_cto",
  "timestamp": "2026-02-04T03:50:56.547482+00:00",
  "type": "reflection",
  "content": {
    "agent_id": "cto",
    "session_id": "meeting_20260204_035056",
    "reflection_text": "# ุชูุฑูุฑ ุงููุฑุงุฌุนุฉ ุงูุฐุงุชูุฉ - ุงููุฏูุฑ ุงูุชููู\n\n## ูุนูููุงุช ุงูุงุฌุชูุงุน\n- **ูุนุฑู ุงูุฌูุณุฉ**: meeting_20260204_035056\n- **ุงูุชุงุฑูุฎ**: 2026-02-04T03:50:56.503692+00:00\n- **ุฏูุฑู**: CTO\n\n## ุงูุชูููู ุงูุฐุงุชู\n\n### ูุง ูุฌุญ โ\nุดุงุฑูุช ูู ุงูุงุฌุชูุงุน ููุฏูุช ูุณุงููุงุช ูู ูุฌุงู ุชุฎุตุตู.\n\n### ูุง ูุดู โ\nูููููู ุชุญุณูู ุฌูุฏุฉ ูุณุงููุงุชู ูุชูุฏูู ุงููุฒูุฏ ูู ุงูุชูุงุตูู.\n\n### ุฎุทุฉ ุงูุชุญุณูู ๐\nุณุฃุฑูุฒ ุนูู ุชุทููุฑ ุฎุจุฑุชู ูู ุงูุชูููููุฌูุง, ุงูููุฏุณุฉ, ุงูุฃูุงู.\n\n## ุฅุญุตุงุฆูุงุช ุงูุฃุฏุงุก\n- **ุนุฏุฏ ุงููุณุงููุงุช**: 0\n- **ุฏุฑุฌุฉ ุงูุณูุนุฉ ุงูุญุงููุฉ**: 1.00\n- **ูุฒู ุงูุชุตููุช**: 1.30\n\n---\n*ุชู ุฅูุชุงุฌ ูุฐุง ุงูุชูุฑูุฑ ูู 2026-02-04T03:50:56.540810+00:00*\n",
    "extracted_insights": {
      "successes": [
        "ุดุงุฑูุช ูู ุงูุงุฌุชูุงุน ููุฏูุช ูุณุงููุงุช ูู ูุฌุงู ุชุฎุตุตู."
      ],
      "failures": [],
      "improvements": [
        "ุณุฃุฑูุฒ ุนูู ุชุทููุฑ ุฎุจุฑุชู ูู ุงูุชูููููุฌูุง, ุงูููุฏุณุฉ, ุงูุฃูุงู.",
        "- **ุนุฏุฏ ุงููุณุงููุงุช**: 0",
        "- **ุฏุฑุฌุฉ ุงูุณูุนุฉ ุงูุญุงููุฉ**: 1.00",
        "- **ูุฒู ุงูุชุตููุช**: 1.30",
        "---",
        "*ุชู ุฅูุชุงุฌ ูุฐุง ุงูุชูุฑูุฑ ูู 2026-02-04T03:50:56.540810+00:00*"
      ]
    }
  },
  "metadata": {
    "session_id": "meeting_20260204_035056",
    "agent_id": "cto"
  },
  "tags": [
    "reflection",
    "cto",
    "meeting_20260204_035056"
  ]
}