{
  "id": "reflection_meeting_20260204_040633_cto",
  "timestamp": "2026-02-04T04:07:29.414435+00:00",
  "type": "reflection",
  "content": {
    "agent_id": "cto",
    "session_id": "meeting_20260204_040633",
    "reflection_text": "# ุชูุฑูุฑ ุงููุฑุงุฌุนุฉ ุงูุฐุงุชูุฉ - ุงููุฏูุฑ ุงูุชููู\n\n## ูุนูููุงุช ุงูุงุฌุชูุงุน\n- **ูุนุฑู ุงูุฌูุณุฉ**: meeting_20260204_040633\n- **ุงูุชุงุฑูุฎ**: 2026-02-04T04:06:33.458731+00:00\n- **ุฏูุฑู**: CTO\n\n## ุงูุชูููู ุงูุฐุงุชู\n\n### ูุง ูุฌุญ โ\nุดุงุฑูุช ูู ุงูุงุฌุชูุงุน ููุฏูุช ูุณุงููุงุช ูู ูุฌุงู ุชุฎุตุตู (ุงูุชูููููุฌูุง, ุงูููุฏุณุฉ, ุงูุฃูุงู).\n\n### ูุง ูุดู โ\nูููููู ุชุญุณูู ุฌูุฏุฉ ูุณุงููุงุชู ูุชูุฏูู ุงููุฒูุฏ ูู ุงูุชูุงุตูู ุงูุชูููุฉ.\n\n### ุฎุทุฉ ุงูุชุญุณูู ๐\nุณุฃุฑูุฒ ุนูู ุชุทููุฑ ุฎุจุฑุชู ูู ุงูุชูููููุฌูุง, ุงูููุฏุณุฉ, ุงูุฃูุงู ูุชุญุณูู ุงูุชูุงุตู ูุน ุงููุฑูู.\n\n## ุฅุญุตุงุฆูุงุช ุงูุฃุฏุงุก\n- **ุนุฏุฏ ุงููุณุงููุงุช**: 7\n- **ุฏุฑุฌุฉ ุงูุณูุนุฉ ุงูุญุงููุฉ**: 1.00\n- **ูุฒู ุงูุชุตููุช**: 1.30\n\n---\n*ุชู ุฅูุชุงุฌ ูุฐุง ุงูุชูุฑูุฑ ูู 2026-02-04T04:07:24.632971+00:00*\n",
    "extracted_insights": {
      "successes": [
        "ุดุงุฑูุช ูู ุงูุงุฌุชูุงุน ููุฏูุช ูุณุงููุงุช ูู ูุฌุงู ุชุฎุตุตู (ุงูุชูููููุฌูุง, ุงูููุฏุณุฉ, ุงูุฃูุงู)."
      ],
      "failures": [],
      "improvements": [
        "- **ุนุฏุฏ ุงููุณุงููุงุช**: 7",
        "- **ุฏุฑุฌุฉ ุงูุณูุนุฉ ุงูุญุงููุฉ**: 1.00",
        "- **ูุฒู ุงูุชุตููุช**: 1.30",
        "---",
        "*ุชู ุฅูุชุงุฌ ูุฐุง ุงูุชูุฑูุฑ ูู 2026-02-04T04:07:24.632971+00:00*"
      ]
    }
  },
  "metadata": {
    "session_id": "meeting_20260204_040633",
    "agent_id": "cto"
  },
  "tags": [
    "reflection",
    "cto",
    "meeting_20260204_040633"
  ]
}